pycreds/__init__.py
pycreds/_pycreds.cp310-win32.pyd
pycreds/_pycreds.pyi
pycreds/cli.py
pycreds/py.typed
pycreds/pycreds.cpp
pycreds/pycreds_darwin.hpp
pycreds/pycreds_posix.hpp
pycreds/pycreds_win.hpp
pycreds-1.1.dist-info/LICENSE.md
pycreds-1.1.dist-info/METADATA
pycreds-1.1.dist-info/WHEEL
pycreds-1.1.dist-info/entry_points.txt
pycreds-1.1.dist-info/top_level.txt
pycreds-1.1.dist-info/RECORD
