Metadata-Version: 2.1
Name: pycreds
Version: 1.1
Summary: Python Library to keep credentials safe by storing in platform keystores.
Home-page: https://github.com/kumaraditya303/pycreds
Author: Kumar Aditya
Author-email: 
License: BSD License
Keywords: credentials,vault
Platform: UNKNOWN
Classifier: Programming Language :: C++
Classifier: Programming Language :: Python
Classifier: Programming Language :: Python :: 3
Classifier: Programming Language :: Python :: 3.7
Classifier: Programming Language :: Python :: 3.8
Classifier: Programming Language :: Python :: 3.9
Classifier: Programming Language :: Python :: 3 :: Only
Classifier: Programming Language :: Python :: Implementation :: CPython
Classifier: Development Status :: 5 - Production/Stable
Classifier: Operating System :: OS Independent
Classifier: Topic :: Security
Classifier: License :: OSI Approved :: BSD License
Requires-Python: >=3.7
License-File: LICENSE.md
Provides-Extra: cli
Requires-Dist: click (==8.0.3) ; extra == 'cli'
